[{
  "_id": {
    "$oid": "64beaf5ca46f87b318db571e"
  },
  "titulo": "LECCION 1 ",
  "categoria": "Clarinete",
  "texto": "Los diferentes tipos de clarinetes: ¿cuántos hay? Los diferentes tipos de clarinetes: ¿cuántos hay?El clarinete es un instrumento de viento madera que produce sonidos a través de la vibración de una lengüeta dentro de la boquilla. Existen varios tipos de clarinetes, cada uno con una longitud y timbre diferentes. Los tipos más comunes son el clarinete soprano, el clarinete bajo y el clarinete contrabajo.El clarinete soprano es el más común y se utiliza regularmente en la música clásica y moderna. Tiene una longitud de alrededor de dos pies y su registro se extiende desde el E por debajo de la clave del bajo hasta el G sobre la clave del agudo. El clarinete bajo, por otro lado, es significativamente más grande que el soprano y se utiliza principalmente en orquestas y bandas de música.\n\nEl clarinete contrabajo es el más grande de todos los clarinetes y es raramente utilizado. Puede tener una longitud de hasta seis pies y es capaz de producir un sonido extremadamente grave y profundo. Además de estos tres, existen otros tipos de clarinetes, como el clarinete en Mi bemos el clarinete piccolo y el clarinete bajo alto.\n\nCada tipo de clarinete tiene su propio conjunto de características que son significativamente diferentes de los demás. Por ejemplo, el clarinete soprano tiene un registro más alto que el bajo, mientras que el clarinete contrabajo tiene un sonido mucho más grave que el resto. Además, los diferentes tipos de clarinetes pueden ser tocados por diferentes niveles de habilidad: algunos son más fáciles de tocar que otros.\n\n\n¿Cuáles son los dos tipos de clarinetes mas utilizados en banda?\nEl clarinete es un instrumento de viento que se utiliza comúnmente en la música clásica, jazz y otros géneros musicales. Hay dos tipos principales de clarinetes: el clarinete en Bb y el clarinete en A.\n\nEl clarinete en Bb es el tipo más común y se utiliza en la mayoría de las bandas de música y conjuntos de música clásica. Tiene un sonido brillante y vibrante que lo hace perfecto para melodías y solos. El clarinete en Bb es muy versátil y se puede utilizar en una amplia variedad de estilos musicales.\n\nEl clarinete en A, por otro lado, suena más suave y cálido que el clarinete en Bb. Se utiliza con mayor frecuencia en la música clásica y se adapta mejor a ciertas piezas musicales que requieren un tono más suave y lírico. El clarinete en A es un poco más grande que el clarinete en Bb y tiene un sonido más profundo y rico.\n\nEs importante destacar que el clarinete bajo y el clarinete contrabajo son también tipos de clarinetes, pero se utilizan con menos frecuencia que los dos tipos principales mencionados anteriormente.\n\nEn resumen, los dos tipos principales de clarinetes son el clarinete en Bb y el clarinete en A. Cada uno tiene su propio sonido y se adapta mejor a ciertos estilos musicales y piezas musicales específicas.\n\n¿Cómo se clasifica el clarinete?\nEl clarinete es un instrumento de viento-madera muy popular en la música clásica y en otros géneros musicales como el jazz o el pop.\n\nExisten varios tipos de clarinetes, cada uno con características distintas que los hacen únicos en cuanto a su sonido y su uso en diferentes géneros musicales.\n\nUno de los clarinetes más populares es el clarinete soprano, que se utiliza frecuentemente en bandas y orquestas. La afinación del clarinete soprano es en si bemol, lo que significa que su sonido es más agudo que el de otros clarinetes.\n\nOtro tipo de clarinete es el clarinete bajo, que tiene una afinación en si bemol, pero su sonido es mucho más grave. El clarinete bajo es utilizado principalmente en música clásica y en orquestas.\n\nEn jazz y música popular, también se utilizan otros tipos de clarinetes, como el clarinete alto y el clarinete contrabajo, que pueden variar en afinación y en su longitud.\n\nEn resumen, los clarinetes se clasifican en función de su afinación, tamaño y uso en diferentes géneros musicales. Cada uno de ellos proporciona un sonido único y diferente por lo que es importante conocerlos y saber cuándo y cómo utilizarlos en la música.\n\n¿Cuál es el clarinete soprano?\nEl clarinete soprano es uno de los instrumentos de viento más populares y conocidos en la música clásica y el jazz. Este instrumento musical pertenece a la familia de los clarinetes, y se caracteriza por su sonido agudo y dulce, que lo hace ideal para melodías y solos.\n\nEste tipo de clarinete es el más utilizado en orquestas y bandas, y se toca en la mayoría de los géneros musicales. El clarinete soprano tiene una longitud de aproximadamente 67 centímetros y su tubo está dividido en tres secciones, que se unen mediante múltiples anillos que permiten ajustar la afinación.\n\nEl cuerpo del clarinete soprano está hecho de madera de gran calidad, y la boquilla está diseñada para producir un sonido cálido y delicado. La embocadura del clarinete soprano es muy importante, y su correcta colocación y uso pueden mejorar significativamente el sonido que se produce.\n\nEl clarinete soprano es un instrumento muy versátil, que se puede utilizar para tocar una gran variedad de géneros musicales, desde la música clásica hasta el jazz. Además, es un instrumento muy popular entre profesionales y aficionados, y se puede encontrar en una gran variedad de tamaños y diseños.\n\nEn conclusión, el clarinete soprano es un instrumento musical maravilloso y muy utilizado en la música. Su sonido agudo y dulce es ideal para solos y melodías, y su cuerpo de madera y su embocadura hacen que produzca un sonido cálido y delicado. Si estás interesado en aprender a tocar un instrumento musical, el clarinete soprano es una excelente opción.\n\n¿Cómo se llama el clarinete más pequeño?\nEl clarinete es uno de los instrumentos de viento más populares y versátiles de la música. Es utilizado en todo tipo de géneros musicales y es conocido por su sonido brillante y agudo. Pero, a medida que vamos profundizando en el mundo de los clarinetes, nos encontramos con diferentes tipos y tamaños de este instrumento, lo que nos lleva a preguntarnos: ¿Cómo se llama el clarinete más pequeño?\n\nEl clarinete más pequeño que existe se llama clarinete piccolo o clarinete sopranino. Este instrumento es de tamaño reducido y tiene una longitud de alrededor de 26 cm. Su sonido es muy agudo y sus notas más bajas suenan como un saxofón soprano. Aunque el piccolo es un clarinete poco común, es utilizado en algunas piezas de música clásica y contemporánea.\n\nA pesar de ser un instrumento pequeño, el clarinete piccolo debe ser tocado por un clarinetista con mucha habilidad y técnica. Debido a su tamaño, el piccolo requiere una gran precisión en la colocación de los dedos y la respiración para conseguir un sonido claro y preciso.\n\nEn conclusión, el clarinete piccolo es el clarinete más pequeño que existe. Este instrumento único puede producir un sonido agudo y brillante, y es utilizado en ocasiones especiales por clarinetistas con habilidades técnicas avanzadas. Si eres un músico interesado en explorar diferentes tipos de clarinetes, el piccolo es una opción interesante para añadir a tu repertorio musical.\n\nEn resumen, hay muchos tipos de clarinetes para elegir, cada uno con su propio conjunto de características y usos. Desde el popular clarinete soprano hasta el raro y grave clarinete contrabajo, hay un clarinete adecuado para cada músico y estilo de música. Sea cual sea el tipo de clarinete que elijas, ¡seguramente estarás en camino a producir hermosos sonidos y disfrutar de la música a lo grande!"
},
{
  "_id": {
    "$oid": "64beaf5ca46f87b318db571f"
  },
  "titulo": "LECCION 1 ",
  "categoria": "Lenguaje musical",
  "texto": "25 CONCEPTOS BÁSICOS DE TEORÍA MUSICAL QUE DEBES CONOCER\nAfinación: Orden como se diferencian las alturas entre sí.\nAfinación exacta o justa: Derivada de los principios físicos de la acústica.\nAfinación temperada: Convencional, no se deriva sólo de la física, sino de la necesidad de unificar criterios a la hora de tocar diversos instrumentos a la vez.\nAltura: Se trata de una metáfora espacial (sinestesia) que expresa la sensación de gravedad o levedad de un sonido periódico; depende de la frecuencia de dicho sonido.\nAltura absoluta: Cuando se fija en relación con una altura de referencia convencional, como la de un diapasón (el la3: 440 Hz).\nAltura relativa: En caso contrario, cuando se fija por su relación con las alturas adyacentes.\nÁmbito: Extensión abarcada por una melodía o un fragmento musical concreto.\nClave: Sirve para proporcionar una nota de referencia a partir de la cual se haga posible la notación de las alturas en el pentagrama. Procede de la denominación alfabética de las notas.\nCompás: División y ordenación de la música en unidades constantes llamadas “tiempos” o “partes”.\nDinámica: En música, la dinámica se refiere a las gradaciones de la intensidad de la música. Existen al menos ocho indicaciones de dinámica (gradaciones de la intensidad de la música), empezando desde un sonido muy bajo, hasta un sonido muy fuerte.\nDominante: en el sistema tonal hace referencia al quinto grado de una escala musical.\nEscala cromática: Ordena ascendentemente los sonidos de una escala, de más grave a más agudo. Se compone de 12 elementos.\nEscala diatónica: Compuesta por los sonidos que comprendidos en una octava, poseen los intervalos básicos.\nEscala: Conjunto de notas ordenadas ascendentemente.\nFrecuencia: Número de períodos por unidad de tiempo. Se mide en segundos y se expresa en Hertz (Hz).\nIntervalo: Distancia entre dos alturas, contando la inicial y la final. Clasificación de los intervalos:\nOído absoluto: Reconocimiento de las alturas en cualquier contexto.\nOído relativo: Capacidad para, desde una referencia calcular las alturas.\nPeriodo: lapso que tarda una vibración.\nRegistro: Extensión general de todos los sonidos, desde el extremo grave al agudo.\nRitmo: Organización en el tiempo de pulsos y acentos que perciben los oyentes como una estructura.\nSíncopa: Efecto rítmico que tiene lugar cuando el sonido de una nota empieza dentro de un tiempo débil y se prolonga hasta uno fuerte.\nTesitura: Extensión de un instrumento en particular.\nTonalidad: Conjunto de sonidos ordenados mediante relaciones mutuas, estando éstas determinadas por un sonido básico llamado Tónica.\nTónica: se llama tónica tanto a la primera nota (o grado) de la escala, como al acorde que se forma a partir de esa primera nota. Ella es la que define la tonalidad, y la que le da su nombre."
},
{
  "_id": {
    "$oid": "64beaf5ca46f87b318db5721"
  },
  "titulo": "LECCION 2 ",
  "categoria": "Clarinete",
  "texto": "Clarinete: Cómo Ensamblar y Afinar\nHoy venimos con un artículo que de seguro te va interesar. Seguimos hablando del clarinete y por supuesto que hay varios aspectos que no tocamos en la entrada anterior. En concreto, el clarinete se considera un instrumento musical perteneciente a la familia de viento, como acompañante de melodías complejas es excelente. Añadido a ello hoy veremos su ensamble y su afinación.\n\nPartes de un clarinete\nBoquilla: esta es la parte donde va colocada la caña y donde se coloca la boca para realizar la embocadura.\nBarrilete: es el elemento donde se puede articular la boquilla con el cuerpo superior del resto del instrumento.\nCuerpo superior: aquí va la mano izquierda cuando se le utiliza y contiene parte del mecanismo a utilizar.\nCuerpo inferior: esta es la parte donde debes colocar la parte derecha al momento de tocar, también se coloca en el parte del mecanismo del instrumento.\nCampana: está situada en la parte inferior y esta cumple una función acústica presentar un sonido cuando es ejecutada.\n\nCómo ensamblar un clarinete\nEnsamblar o armar un clarinete no es complicado si tienes la guía correcta, pues bien vamos allá y preparemos un excelente instrumento. A continuación te mencionamos los pasos que debes seguir:\n\nEn las parte de la boquilla debes colocar al caña,ahora utiliza una abrazadera para sostenerla fijamente.\nSeguidamente debes iniciar a ensamblar el clarinete.\nLa parte superior se le conoce como pabellón. Esta parte la tomamos y la insertamos en el resto del cuerpo, procura presionar fuertemente las llaves para que se inserte adecuadamente.\nAhora coloca la boquilla, finalmente aprieta los tornillos y listo, ya está armado un clarinete.\nConsejos para armar un clarinete\nQuizá como primera recomendación sería que no empieces a armar sin conocer las partes del clarinete. Si no las conoces investiga o sigue el manual para que no dañes ninguna de ellas. Cuando hayas armado debes verificar que cada una de ellas esté en el lugar correcto para que la ejecución de la misma sea perfecta.\n\nCómo se afina un clarinete\nLa importancia de afinar un clarinete es fundamental para poder desarrollar un sonido elegante y exquisito para el oído. No importa si tocas en una orquesta, sinfónica, banda o en tu casa, debes aprender a realizar el proceso de afinamiento. Con ese fin hemos preparado un método efectivo a seguir.\n\nMétodo 1: calentando el clarinete\nCuando estás ejecutando el clarinete por un largo periodo este suele calentarse por tu aliento. A medida que se va aumentando la temperatura por su aliento o por el ambiente, su sonido se irá agudizando. Este instrumento cambia su tonalidad con la temperatura, sin embargo, el calor es el que más reciente, por ello y para mantener un equilibrio desde el inicio procura calentarlo antes de tocar.\nProcura tocar la nota mi grave. Para este ejercicio solo debes colocar tu mano derecha en la tecla más grave de Mi pero procura no tocar ninguna otra más. Lo que sucede con este procedimiento es que esparces el aire dentro del clarinete de una manera más efectiva.\nSopla aire a través del instrumento. Primero respira hondo y luego sopla el aire a través del instrumento. Recuerda no emplear ninguna nota cuando realices está técnica. Esta es otra manera para poder calentar tu clarinete, hazlo por unos cinco minutos.\nPuedes tocar escalas. El calentado del clarinete se puede dar a través de la práctica de unas cuantas escalas. Puedes iniciar tocando unas cuantas escalas menores, luego puedes pasar a mayores y finalmente a pentatónicas. Quizá al inicio no suene tan afinado pero es importante repetir este procedimiento varias veces. Si lo deseas puedes practicar algunas melodías que estés por ejecutar.\n\nMétodo 2: afinamiento personal\nComprendiendo las claves del clarinete. Con los clarinetes tienes la capacidad de trasponerte para igual las claves que has escuchado de otros músicos. Si tienes un clarinete estándar iniciarás con un tono completo más bajo. En concreto, casi todos los instrumentos logran un Do tocando una nota Do, pero en el caso del clarinete debes tocar la nota Re para lograr el sonido de la nota Do.\nEsta es una de las razones por las cuales las personas han categorizado al clarinete como un instrumento traspone. ¿Qué es trasponer? Significa que debes arreglar las notas para que puedan encajar con el instrumento. En el caso del clarinete debes subir un tono completo por cada nota.\n\nUtilizando un afinador cromático. Este tipo de instrumento son sugeridos para músicos que tienen un nivel intermedio en adelante. El precio estándar de un afinador cromático en el mercado es de $25 USD. Pero de igual manera puedes descargar una App de este tipo para tu Smartphone. Estos son perfectos ya que te muestran la nota que estás tocando. Procura que éste tenga un micrófono en lugar de utilizarlo como un pedal de guitarra. Si deseas puedes afinar en varias claves, pero recomendamos iniciar con el Do de concierto. El Do de concierto viene siendo Re en la mayoría de los clarinetes.\nTocando la octava más grave. Siempre es recomendable afinar un clarinete tocando un registro más bajo y seguir así a las otras secciones. Si tienes un afinador inicia tocando un Re grave. Si lo estás haciendo bien el afinador detectará la nota como un Do. Pero si no lo muestra no te preocupes pues sabrás que debes afinarla.\nAjustando el barril. Si has realizado los ejercicios anteriores podrás realizar este procedimiento. Ajustar el barril para afinar es una de las mejores opciones para mejorar la octava más grave. En el caso de las notas agudas deberás extender el instrumento.\nInicia haciendo unos ajustes iniciales al barril superior con alrededor de medio milímetro, lo puedes hacer empujando o jalando. Ahora toca la misma nota y mira el afinador para ver los cambios.\n\nConsejos finales para afinar\nAfinar bien significa que puedes tocar un sonido completo, si no logras afinar como tocarías entonces no serviría de nada el procedimiento.\nAfinar al oído es importante pero requiere una experiencia musical importante, sin embargo por ello existen los afinadores electrónicos, ellos incluso son más eficientes.\nPuedes jalar la campana un poco hacia afuera para que afines la notas y lograr que se utilice toda la longitud del instrumento.\n\nEn la proxima leccion comenzaremos a practicar nuestra respiracion, emisicion de aire y ejercicios de lengua sobre la caña.Esto ya empieza a sonar! ;)"
},
{
  "_id": {
    "$oid": "64beaf5ca46f87b318db5722"
  },
  "titulo": "LECCION 2 ",
  "categoria": "Lenguaje musical",
  "texto": "Contenido disponible proximamente"
},
{
  "_id": {
    "$oid": "64beaf5ca46f87b318db571d"
  },
  "titulo": "LECCION 1 ",
  "categoria": "Ukelele",
  "texto": "Cuando hablamos de tipos de ukelele no solo nos referimos al tamaño. Sí, el tamaño es una característica, pero eso hace que cambie el sonido, la comodidad y ¡hasta la afinación!\n\nLos 4 tipos de ukeleles principales son:\nSoprano\nConcierto\nTenor\nBarítono\n\nAunque para los músicos avanzados es cuestión de preferencia, los principiantes necesitan saber cuál es el mejor tipo de ukelele empezar.\n¡Y para eso hemos creado esta guía!\n\nUkelele Soprano\nEl soprano es el tipo más tradicional y el tamaño que asocia normalmente la gente cuando hablamos de ukeleles.\nTiene ese sonido clásico que identificamos con el ukelele, pero tener el tamaño más pequeño de la familia tiene dos \"inconvenientes\":\nEste tipo de ukelele tiene menos volumen que sus hermanos mayores y un tamaño complicado para manos grandes.\nLa ventaja principal es que te lo puedes llevar a cualquier lado y animar fiestas en la playa\nCaracterísticas tamaño Soprano:\nMedidas ukelele soprano: 53cm / 21 pulgadas\nMedida de la escala: 33-35,5 cm / 13-14 pulgadas\nAfinación: GCEA / SOL DO MI LA\n\nUkelele Concierto\nEl ukelele concierto tiene un tamaño algo mayor que su hermano pequeño lo que le da algunas ventajas:\nEl cuerpo es más grande, por lo que ganamos resonancia (volumen) y conseguimos un tono más cálido sin perder el sonido icónico del ukelele.\nAdemás, con un mástil más largo tenemos más espacio en los trastes y resulta mucho más cómodo de tocar.\nPor otra parte, aunque es un poco más grande, todavía es relativamente cómodo de transportar.\nCaracterísticas tamaño Concierto:\nMedidas ukelele concierto: 58 cm / 23 pulgadas\nMedida de la escala: 33-35,5 cm / 15-16 pulgadas\nAfinación: GCEA / SOL DO MI LA\n\nUkelele Tenor\nAquí ya empezamos a perder el sonido tradicional del ukelele y se empieza a parecer más al de una guitarra. Por eso muchos aficionados prefieren los tipos de ukelele anteriores en vez de el tamaño tenor.\nPor otra parte, este tamaño de ukelele es común entre los músicos profesionales ya que una escala más larga permite más tensión en las cuerdas y facilita los punteos con los dedos.\nSi eres principiante y estás buscando tu primer ukelele, probablemente este no sea el tipo ideal.\nCaracterísticas tamaño Tenor:\nMedidas ukelele tenor: 66 cm / 26 pulgadas\nMedida de la escala: 33-35,5 cm / 17-18 pulgadas\nAfinación: GCEA / SOL DO MI LA\n\nUkelele Barítono\nEl barítono es el tipo de ukelele más grande que puedes encontrar. Casi parece una guitarra pequeña más que un ukelele.\nDe hecho, la afinación del ukelele barítono es igual a la de una guitarra sin las dos cuerdas de arriba, por lo que perdemos casi por completo el sonido clásico del ukelele.\nY aunque se separa de lo tradicional, este tamaño de ukelele es usado por algunos músicos de jazz que buscan innovar con un sonido único.\nCaracterísticas tamaño Barítono:\nMedidas ukelele barítono: 76 cm / 30 pulgadas\nMedida de la escala: 33-35,5 cm / 19-20 pulgadas\nAfinación: DGBE / RE SOL SI MI\n\nEntonces, ¿Qué tipo de ukelele comprar?\nLo primero: si te estás haciendo esta pregunta es que probablemente vas a comprar tu primer ukelele\n¡No pasa nada! Todos hemos pasado por ahí y para eso estamos nosotros.\nNuestra recomendación para principiantes son los dos tamaños de ukelele más pequeños:\nUkelele soprano: El sonido clásico con el tamaño compacto que nos permite llevarlo a todas partes. Muchas opciones de colores y estilos.\n\nUkelele concierto: Un poco más grande, con un sonido más cálido. Perdemos algo en portabilidad (no mucho), pero ganamos en comodidad si tenemos manos grandes.\n\nCualquiera de estos dos tamaños es perfecto para empezar con el instrumento.\n\nOtros tipos de ukelele curiosos\nY ahora que el instrumento se ha vuelto tan popular, además de las medidas y tamaños, los fabricantes están experimentando con todo tipo de ukeleles innovando tanto en diseño como sonido.\nEstos tipos de ukeleles no son para principiantes, pero algunos son muy curiosos y merece la pena conocerlos.\nUkelele piña o pineapple\nEste tipo de ukelele tiene el mismo tamaño que un soprano, pero con un cuerpo en forma de piña. Gracias a esto, ganamos en volumen.\nAunque alguna marca sigue fabricando este tamaño hoy en día, los originales diseñados por Samuel Kamaka en los años 20 son a día de hoy objeto de coleccionistas.\n\nUkelele nano o sopranissimo\nCasi podríamos decir ukelele de bolsillo\nCon menos de 30 centímetros, es perfecto para llevarlo a cualquier sitio y sacarle partido a sus 10 trastes.\n\nUkelele Sopranino\nEste tipo está justo un paso por debajo del ukelele soprano clásico en cuanto a tamaño.\n\nUkelele bajo\nMás grande que un ukelele barítono con cuerdas gruesas afinado igual que un bajo tradicional.\nDigamos que es más cómodo que transportar un bajo eléctrico y tiene un tono similar al del contrabajo. Perfecto para pequeños grupos acústicos de jazz, bluegrass, country...\n\nUkulele \"cuello largo\" o super ukelele\nLos aficionados lo conocemos como el \"cuello largo\", pero los fabricantes lo están vendiendo como \"super ukelele\".\nSimplemente son ukeleles con el cuerpo de un tamaño y el mástil de otro distinto. Por ejemplo, un cuerpo de soprano con un mástil de concierto.\n\nGuitalele\nEn realidad es una guitarra con tamaño de ukelele. Tiene 6 cuerdas y lleva una afinación ADGCEA.\nEs como si a una guitarra clásica le ponemos un capo en el quinto traste."
},
{
  "_id": {
    "$oid": "64beaf5ca46f87b318db5720"
  },
  "titulo": "LECCION 2 ",
  "categoria": "Ukelele",
  "texto": "Sin duda, afinar el ukelele hará una gran diferencia si eres un principiante.\nIncluso si está haciendo un gran progreso con las técnicas y está poniendo mucho esfuerzo en aprender sus acordes, si no tiene en cuenta afinar su ukelele, sus canciones no sonarán bien, y si su ukelele es demasiado desafinadas, es posible que las canciones no tengan ningún sentido, para empezar.\nHay muchas formas diferentes de afinar tu ukelele. Los cubriremos en este artículo, así que sin más preámbulos, saltemos a él.\n\nCómo afinar correctamente tu ukelele\n1. Aprenda la afinación básica de cuerdas abiertas:\nUna forma rápida de resumirlo sería G – C – E – A\nDe bajo a alto, la cuarta cuerda se afina G, la tercera se afina C, la segunda se afina E y la primera se afina A.\nSin embargo, afinar un ukelele depende de su tamaño. Hay cuatro tamaños diferentes de ukeleles; soprano, concierto, tenor y barítono.\nLos primeros tres ukeleles suelen estar afinados como se mencionó anteriormente, pero el barítono está afinado D – G – B – E.\nSi tiene su ukelele afinado como se mencionó anteriormente, está en afinación estándar, y esta es la afinación que necesita para tocar la mayoría de las canciones.\nAlgo popular entre muchos guitarristas y jugadores de ukelele es que en la afinación estándar, un ukelele está afinado para que suene igual que las 4 cuerdas superiores de la guitarra. Esto es esencialmente cierto si tiene un capo en el quinto traste de su guitarra.\n2. Uso de un afinador electrónico para afinar su ukelele\nEsta es la forma más sencilla y fácil de afinar su ukelele.\nLa primera forma de utilizar un sintonizador electrónico es obtener una aplicación en su teléfono inteligente.\nEsto puede ser un poco difícil si está afinando su ukelele en un lugar ruidoso, pero ese no es el caso y, personalmente, lo encuentro bastante conveniente.\nOtra cosa que puede probar son las abrazaderas de sintonizador con clip.\nEstos clips funcionan de forma un poco diferente a las aplicaciones. En lugar de detectar el tono a través del micrófono, detectan las vibraciones cuando las colocas en el cabezal del ukelele.\nEstos sintonizadores de clip tienen la ventaja de no verse afectados por el ruido que tiene a su alrededor mientras afina su ukelele.\nLa última y más profesional forma de afinar su ukelele con un afinador electrónico sería conectarlo a un afinador de pedal.\n3. Afinando su ukelele a un piano\nOtra forma sencilla de afinar tu ukelele es depender de tus oídos y afinarlo con un piano.\nEs realmente fácil una vez que te acostumbras porque, para algunas personas, puede tomar un poco de tiempo acostumbrarse, especialmente si nunca antes han tocado la guitarra o el piano, por lo que no tienen experiencia alguna en cómo suenan las notas. igual que.\nGCEA corresponde a sol do mi la. Si está afinando esto con un piano, vaya a la C central, y debería sonar igual que la C en su ukelele, omita una tecla y la tecla después es E, luego omita otra tecla y la siguiente es G y la tecla uno justo al lado es A.\n4. Afinación de su ukelele a sí mismo (afinación relativa del ukelele)\nEste es el método menos preciso para afinar su ukelele; sin embargo, puede resultar útil si está practicando solo o si desea tocar su ukelele y no tiene un afinador cerca.\nEn este método, compararás melodías similares en diferentes cuerdas y trastes entre sí; por eso este método no es realmente exacto.\nPruebe los siguientes pasos en orden.\nToque su cuerda A (primera cuerda) abierta y escuche con atención.\nPonga sus dedos en el quinto traste (segunda cuerda) de la cuerda Mi; debería sonar igual que la cuerda A abierta.\nColoque su dedo en el cuarto traste de la cuerda C (la tercera cuerda), y debería sonar igual que tocar la cuerda Mi abierta.\nLuego viene afinando la cuerda G, ahora esto depende de si estás afinando un G alto o un G bajo:\nSi está afinando una cuerda G alta, coloque su dedo en el segundo traste en la cuerda G, y debería tocar una nota A, en otras palabras, debería sonar como tocar la cuerda A abierta.\nSi está afinando una nota G baja, coloque su dedo en el quinto traste de la cuerda G, y ahora está tocando una nota C, es decir, debería sonar igual que tocar la cuerda C abierta.\nAhora bien, este método podría ser un poco confuso al principio, lo sé, pero a mi modo de ver, incluso si tiene otros métodos para afinar su ukelele, practique este método porque nunca sabe cuándo puede ser útil.\nAquí tienes un consejo si vas a tocar con tus amigos y no tienes un sintonizador. Afina cualquiera de las cuerdas de tu ukelele para que suene igual que las de tus amigos y sigue adelante.\nAdemás, y esto es algo que lo ayudará a sonar un poco menos desafinado pero no necesariamente preciso, intente afinar sus cuerdas en relación con su cuerda C porque resulta que mantiene su afinación por más tiempo.\nCómo afinar un ukelele,Ultimas palabras\nUna vez que domine la afinación de su ukelele, notará lo diferente que suena su música y se enamorará aún más de este instrumento, al igual que su público. ¡Disfruta de tu viaje de tuning!"
}]